binformat.py
binformat-1.0.2.dist-info/LICENSE
binformat-1.0.2.dist-info/WHEEL
binformat-1.0.2.dist-info/METADATA
binformat-1.0.2.dist-info/RECORD
