Metadata-Version: 2.1
Name: binformat
Version: 1.0.2
Summary: Implementation of the Permuatio wire format
Home-page: https://codeberg.org/Patpine/binformat-py
License: AGPL
Author: Arcade Wise
Author-email: l3gacy.b3ta@gmail.com
Requires-Python: >=3.10,<4.0
Classifier: License :: Other/Proprietary License
Classifier: Programming Language :: Python :: 3
Classifier: Programming Language :: Python :: 3.10
Project-URL: Bug Tracker, https://codeberg.org/Patpine/binformat-py/issues
Project-URL: Repository, https://codeberg.org/Patpine/binformat-py
